odoo/addons/sale_exception_product_sale_manufactured_for/README.rst
odoo/addons/sale_exception_product_sale_manufactured_for/__init__.py
odoo/addons/sale_exception_product_sale_manufactured_for/__manifest__.py
odoo/addons/sale_exception_product_sale_manufactured_for/data/exception_rule.xml
odoo/addons/sale_exception_product_sale_manufactured_for/demo/exception_rule.xml
odoo/addons/sale_exception_product_sale_manufactured_for/i18n/sale_exception_product_sale_manufactured_for.pot
odoo/addons/sale_exception_product_sale_manufactured_for/models/__init__.py
odoo/addons/sale_exception_product_sale_manufactured_for/models/sale_order.py
odoo/addons/sale_exception_product_sale_manufactured_for/readme/CONTRIBUTORS.rst
odoo/addons/sale_exception_product_sale_manufactured_for/readme/CREDITS.rst
odoo/addons/sale_exception_product_sale_manufactured_for/readme/DESCRIPTION.rst
odoo/addons/sale_exception_product_sale_manufactured_for/static/description/icon.png
odoo/addons/sale_exception_product_sale_manufactured_for/static/description/index.html
odoo/addons/sale_exception_product_sale_manufactured_for/tests/__init__.py
odoo/addons/sale_exception_product_sale_manufactured_for/tests/test_sale_exception.py
odoo14_addon_sale_exception_product_sale_manufactured_for-14.0.1.1.0.dist-info/METADATA
odoo14_addon_sale_exception_product_sale_manufactured_for-14.0.1.1.0.dist-info/WHEEL
odoo14_addon_sale_exception_product_sale_manufactured_for-14.0.1.1.0.dist-info/top_level.txt
odoo14_addon_sale_exception_product_sale_manufactured_for-14.0.1.1.0.dist-info/RECORD
