Metadata-Version: 2.1
Name: odoo14-addon-sale-exception-product-sale-manufactured-for
Version: 14.0.1.1.0
Summary: The partner set in the sales order can order only if he/she has a commercial entity that is listed as one of the partners for which the products can be manufactured for.
Home-page: https://github.com/OCA/sale-workflow
Author: Camptocamp, Odoo Community Association (OCA)
Author-email: support@odoo-community.org
License: AGPL-3
Platform: UNKNOWN
Classifier: Programming Language :: Python
Classifier: Framework :: Odoo
Classifier: Framework :: Odoo :: 14.0
Classifier: License :: OSI Approved :: GNU Affero General Public License v3
Requires-Python: >=3.6
Requires-Dist: odoo14-addon-product-sale-manufactured-for
Requires-Dist: odoo14-addon-sale-exception
Requires-Dist: odoo <14.1dev,>=14.0a
